[
  { "id": 1, "character": "一", "meaning": "one", "stroke_count": 1, "reading": "いち" },
  { "id": 2, "character": "丨", "meaning": "line", "stroke_count": 1, "reading": "ぼう" },
  { "id": 3, "character": "丶", "meaning": "dot", "stroke_count": 1, "reading": "てん" },
  { "id": 4, "character": "丿", "meaning": "slash", "stroke_count": 1, "reading": "の" },
  { "id": 5, "character": "乙", "meaning": "second", "stroke_count": 1, "reading": "おつ" },
  { "id": 6, "character": "亅", "meaning": "hook", "stroke_count": 1, "reading": "はねぼう" },
  { "id": 7, "character": "二", "meaning": "two", "stroke_count": 2, "reading": "に" },
  { "id": 8, "character": "亠", "meaning": "lid", "stroke_count": 2, "reading": "なべぶた" },
  { "id": 9, "character": "人", "meaning": "person", "stroke_count": 2, "reading": "ひと" },
  { "id": 10, "character": "儿", "meaning": "legs", "stroke_count": 2, "reading": "にんにょう" },
  { "id": 11, "character": "入", "meaning": "enter", "stroke_count": 2, "reading": "いる" },
  { "id": 12, "character": "八", "meaning": "eight", "stroke_count": 2, "reading": "はち" },
  { "id": 13, "character": "冂", "meaning": "down box", "stroke_count": 2, "reading": "けいがまえ" },
  { "id": 14, "character": "冖", "meaning": "cover", "stroke_count": 2, "reading": "わかんむり" },
  { "id": 15, "character": "冫", "meaning": "ice", "stroke_count": 2, "reading": "にすい" },
  { "id": 16, "character": "几", "meaning": "table", "stroke_count": 2, "reading": "きにょう" },
  { "id": 17, "character": "凵", "meaning": "open box", "stroke_count": 2, "reading": "かんにょう" },
  { "id": 18, "character": "刀", "meaning": "knife", "stroke_count": 2, "reading": "かたな" },
  { "id": 19, "character": "力", "meaning": "power", "stroke_count": 2, "reading": "ちから" },
  { "id": 20, "character": "勹", "meaning": "wrap", "stroke_count": 2, "reading": "つつみがまえ" },
  { "id": 21, "character": "匕", "meaning": "spoon", "stroke_count": 2, "reading": "さじ" },
  { "id": 22, "character": "匚", "meaning": "box", "stroke_count": 2, "reading": "はこがまえ" },
  { "id": 23, "character": "匸", "meaning": "hiding enclosure", "stroke_count": 2, "reading": "かくしがまえ" },
  { "id": 24, "character": "十", "meaning": "ten", "stroke_count": 2, "reading": "じゅう" },
  { "id": 25, "character": "卜", "meaning": "divination", "stroke_count": 2, "reading": "ぼく" },
  { "id": 26, "character": "卩", "meaning": "seal", "stroke_count": 2, "reading": "ふしづくり" },
  { "id": 27, "character": "厂", "meaning": "cliff", "stroke_count": 2, "reading": "がんだれ" },
  { "id": 28, "character": "厶", "meaning": "private", "stroke_count": 2, "reading": "む" },
  { "id": 29, "character": "又", "meaning": "again", "stroke_count": 2, "reading": "また" },
  { "id": 30, "character": "口", "meaning": "mouth", "stroke_count": 3, "reading": "くち" },
  { "id": 31, "character": "囗", "meaning": "enclosure", "stroke_count": 3, "reading": "くにがまえ" },
  { "id": 32, "character": "土", "meaning": "earth", "stroke_count": 3, "reading": "つち" },
  { "id": 33, "character": "士", "meaning": "scholar", "stroke_count": 3, "reading": "さむらい" },
  { "id": 34, "character": "夂", "meaning": "go", "stroke_count": 3, "reading": "ふゆがしら" },
  { "id": 35, "character": "夊", "meaning": "go slowly", "stroke_count": 3, "reading": "すいにょう" },
  { "id": 36, "character": "夕", "meaning": "evening", "stroke_count": 3, "reading": "ゆうべ" },
  { "id": 37, "character": "大", "meaning": "big", "stroke_count": 3, "reading": "だい" },
  { "id": 38, "character": "女", "meaning": "woman", "stroke_count": 3, "reading": "おんな" },
  { "id": 39, "character": "子", "meaning": "child", "stroke_count": 3, "reading": "こ" },
  { "id": 40, "character": "宀", "meaning": "roof", "stroke_count": 3, "reading": "うかんむり" },
  { "id": 41, "character": "寸", "meaning": "inch", "stroke_count": 3, "reading": "すん" },
  { "id": 42, "character": "小", "meaning": "small", "stroke_count": 3, "reading": "しょう" },
  { "id": 43, "character": "尢", "meaning": "lame", "stroke_count": 3, "reading": "まげあし" },
  { "id": 44, "character": "尸", "meaning": "corpse", "stroke_count": 3, "reading": "しかばね" },
  { "id": 45, "character": "屮", "meaning": "sprout", "stroke_count": 3, "reading": "てつ" },
  { "id": 46, "character": "山", "meaning": "mountain", "stroke_count": 3, "reading": "やま" },
  { "id": 47, "character": "巛", "meaning": "river", "stroke_count": 3, "reading": "かわ" },
  { "id": 48, "character": "工", "meaning": "work", "stroke_count": 3, "reading": "こう" },
  { "id": 49, "character": "己", "meaning": "oneself", "stroke_count": 3, "reading": "おのれ" },
  { "id": 50, "character": "巾", "meaning": "turban", "stroke_count": 3, "reading": "はば" },
  { "id": 51, "character": "干", "meaning": "dry", "stroke_count": 3, "reading": "ほす" },
  { "id": 52, "character": "幺", "meaning": "short thread", "stroke_count": 3, "reading": "いとがしら" },
  { "id": 53, "character": "广", "meaning": "dotted cliff", "stroke_count": 3, "reading": "まだれ" },
  { "id": 54, "character": "廴", "meaning": "long stride", "stroke_count": 3, "reading": "えんにょう" },
  { "id": 55, "character": "廾", "meaning": "two hands", "stroke_count": 3, "reading": "にじゅうあし" },
  { "id": 56, "character": "弋", "meaning": "shoot", "stroke_count": 3, "reading": "しきがまえ" },
  { "id": 57, "character": "弓", "meaning": "bow", "stroke_count": 3, "reading": "ゆみ" },
  { "id": 58, "character": "彐", "meaning": "snout", "stroke_count": 3, "reading": "けいがしら" },
  { "id": 59, "character": "彡", "meaning": "bristle", "stroke_count": 3, "reading": "さんづくり" },
  { "id": 60, "character": "彳", "meaning": "step", "stroke_count": 3, "reading": "ぎょうにんべん" },
  { "id": 61, "character": "心", "meaning": "heart", "stroke_count": 4, "reading": "こころ" },
  { "id": 62, "character": "戈", "meaning": "halberd", "stroke_count": 4, "reading": "ほこ" },
  { "id": 63, "character": "戶", "meaning": "door", "stroke_count": 4, "reading": "と" },
  { "id": 64, "character": "手", "meaning": "hand", "stroke_count": 4, "reading": "て" },
  { "id": 65, "character": "支", "meaning": "branch", "stroke_count": 4, "reading": "し" },
  { "id": 66, "character": "攴", "meaning": "rap", "stroke_count": 4, "reading": "ぼくづくり" },
  { "id": 67, "character": "文", "meaning": "script", "stroke_count": 4, "reading": "ぶん" },
  { "id": 68, "character": "斗", "meaning": "dipper", "stroke_count": 4, "reading": "と" },
  { "id": 69, "character": "斤", "meaning": "axe", "stroke_count": 4, "reading": "おのづくり" },
  { "id": 70, "character": "方", "meaning": "square", "stroke_count": 4, "reading": "ほう" },
  { "id": 71, "character": "无", "meaning": "not", "stroke_count": 4, "reading": "なし" },
  { "id": 72, "character": "日", "meaning": "sun", "stroke_count": 4, "reading": "ひ" },
  { "id": 73, "character": "曰", "meaning": "say", "stroke_count": 4, "reading": "いわく" },
  { "id": 74, "character": "月", "meaning": "moon", "stroke_count": 4, "reading": "つき" },
  { "id": 75, "character": "木", "meaning": "tree", "stroke_count": 4, "reading": "き" },
  { "id": 76, "character": "欠", "meaning": "lack", "stroke_count": 4, "reading": "あくび" },
  { "id": 77, "character": "止", "meaning": "stop", "stroke_count": 4, "reading": "とめる" },
  { "id": 78, "character": "歹", "meaning": "death", "stroke_count": 4, "reading": "がつへん" },
  { "id": 79, "character": "殳", "meaning": "weapon", "stroke_count": 4, "reading": "るまた" },
  { "id": 80, "character": "毋", "meaning": "do not", "stroke_count": 4, "reading": "なかれ" },
  { "id": 81, "character": "比", "meaning": "compare", "stroke_count": 4, "reading": "くらべる" },
  { "id": 82, "character": "毛", "meaning": "fur", "stroke_count": 4, "reading": "け" },
  { "id": 83, "character": "氏", "meaning": "clan", "stroke_count": 4, "reading": "うじ" },
  { "id": 84, "character": "气", "meaning": "steam", "stroke_count": 4, "reading": "きがまえ" },
  { "id": 85, "character": "水", "meaning": "water", "stroke_count": 4, "reading": "みず" },
  { "id": 86, "character": "火", "meaning": "fire", "stroke_count": 4, "reading": "ひ" },
  { "id": 87, "character": "爪", "meaning": "claw", "stroke_count": 4, "reading": "つめ" },
  { "id": 88, "character": "父", "meaning": "father", "stroke_count": 4, "reading": "ちち" },
  { "id": 89, "character": "爻", "meaning": "double x", "stroke_count": 4, "reading": "こう" },
  { "id": 90, "character": "爿", "meaning": "split wood", "stroke_count": 4, "reading": "しょうへん" },
  { "id": 91, "character": "片", "meaning": "slice", "stroke_count": 4, "reading": "かた" },
  { "id": 92, "character": "牙", "meaning": "fang", "stroke_count": 4, "reading": "きば" },
  { "id": 93, "character": "牛", "meaning": "cow", "stroke_count": 4, "reading": "うし" },
  { "id": 94, "character": "犬", "meaning": "dog", "stroke_count": 4, "reading": "いぬ" },
  { "id": 95, "character": "玄", "meaning": "profound", "stroke_count": 5, "reading": "げん" },
  { "id": 96, "character": "玉", "meaning": "jade", "stroke_count": 5, "reading": "たま" },
  { "id": 97, "character": "瓜", "meaning": "melon", "stroke_count": 5, "reading": "うり" },
  { "id": 98, "character": "瓦", "meaning": "tile", "stroke_count": 5, "reading": "かわら" },
  { "id": 99, "character": "甘", "meaning": "sweet", "stroke_count": 5, "reading": "あまい" },
  { "id": 100, "character": "生", "meaning": "life", "stroke_count": 5, "reading": "せい" },
  { "id": 101, "character": "用", "meaning": "use", "stroke_count": 5, "reading": "もちいる" },
  { "id": 102, "character": "田", "meaning": "field", "stroke_count": 5, "reading": "た" },
  { "id": 103, "character": "疋", "meaning": "bolt of cloth", "stroke_count": 5, "reading": "ひき" },
  { "id": 104, "character": "疒", "meaning": "sickness", "stroke_count": 5, "reading": "やまいだれ" },
  { "id": 105, "character": "癶", "meaning": "dotted tent", "stroke_count": 5, "reading": "はつがしら" },
  { "id": 106, "character": "白", "meaning": "white", "stroke_count": 5, "reading": "しろ" },
  { "id": 107, "character": "皮", "meaning": "skin", "stroke_count": 5, "reading": "かわ" },
  { "id": 108, "character": "皿", "meaning": "dish", "stroke_count": 5, "reading": "さら" },
  { "id": 109, "character": "目", "meaning": "eye", "stroke_count": 5, "reading": "め" },
  { "id": 110, "character": "矛", "meaning": "spear", "stroke_count": 5, "reading": "ほこ" },
  { "id": 111, "character": "矢", "meaning": "arrow", "stroke_count": 5, "reading": "や" },
  { "id": 112, "character": "石", "meaning": "stone", "stroke_count": 5, "reading": "いし" },
  { "id": 113, "character": "示", "meaning": "spirit", "stroke_count": 5, "reading": "しめす" },
  { "id": 114, "character": "禸", "meaning": "track", "stroke_count": 5, "reading": "ぐうのあし" },
  { "id": 115, "character": "禾", "meaning": "grain", "stroke_count": 5, "reading": "のぎ" },
  { "id": 116, "character": "穴", "meaning": "cave", "stroke_count": 5, "reading": "あな" },
  { "id": 117, "character": "立", "meaning": "stand", "stroke_count": 5, "reading": "たつ" },
  { "id": 118, "character": "竹", "meaning": "bamboo", "stroke_count": 6, "reading": "たけ" },
  { "id": 119, "character": "米", "meaning": "rice", "stroke_count": 6, "reading": "こめ" },
  { "id": 120, "character": "糸", "meaning": "silk", "stroke_count": 6, "reading": "いと" },
  { "id": 121, "character": "缶", "meaning": "jar", "stroke_count": 6, "reading": "かん" },
  { "id": 122, "character": "网", "meaning": "net", "stroke_count": 6, "reading": "あみがしら" },
  { "id": 123, "character": "羊", "meaning": "sheep", "stroke_count": 6, "reading": "ひつじ" },
  { "id": 124, "character": "羽", "meaning": "feather", "stroke_count": 6, "reading": "はね" },
  { "id": 125, "character": "老", "meaning": "old", "stroke_count": 6, "reading": "おいる" },
  { "id": 126, "character": "而", "meaning": "and", "stroke_count": 6, "reading": "しこうして" },
  { "id": 127, "character": "耒", "meaning": "plow", "stroke_count": 6, "reading": "すきへん" },
  { "id": 128, "character": "耳", "meaning": "ear", "stroke_count": 6, "reading": "みみ" },
  { "id": 129, "character": "聿", "meaning": "brush", "stroke_count": 6, "reading": "ふでづくり" },
  { "id": 130, "character": "肉", "meaning": "meat", "stroke_count": 6, "reading": "にく" },
  { "id": 131, "character": "臣", "meaning": "minister", "stroke_count": 6, "reading": "しん" },
  { "id": 132, "character": "自", "meaning": "self", "stroke_count": 6, "reading": "みずから" },
  { "id": 133, "character": "至", "meaning": "arrive", "stroke_count": 6, "reading": "いたる" },
  { "id": 134, "character": "臼", "meaning": "mortar", "stroke_count": 6, "reading": "うす" },
  { "id": 135, "character": "舌", "meaning": "tongue", "stroke_count": 6, "reading": "した" },
  { "id": 136, "character": "舛", "meaning": "oppose", "stroke_count": 6, "reading": "まいあし" },
  { "id": 137, "character": "舟", "meaning": "boat", "stroke_count": 6, "reading": "ふね" },
  { "id": 138, "character": "艮", "meaning": "stopping", "stroke_count": 6, "reading": "こん" },
  { "id": 139, "character": "色", "meaning": "color", "stroke_count": 6, "reading": "いろ" },
  { "id": 140, "character": "艸", "meaning": "grass", "stroke_count": 6, "reading": "くさ" },
  { "id": 141, "character": "虍", "meaning": "tiger", "stroke_count": 6, "reading": "とらがしら" },
  { "id": 142, "character": "虫", "meaning": "insect", "stroke_count": 6, "reading": "むし" },
  { "id": 143, "character": "血", "meaning": "blood", "stroke_count": 6, "reading": "ち" },
  { "id": 144, "character": "行", "meaning": "go", "stroke_count": 6, "reading": "いく" },
  { "id": 145, "character": "衣", "meaning": "clothes", "stroke_count": 6, "reading": "ころも" },
  { "id": 146, "character": "襾", "meaning": "west", "stroke_count": 6, "reading": "にし" },
  { "id": 147, "character": "見", "meaning": "see", "stroke_count": 7, "reading": "みる" },
  { "id": 148, "character": "角", "meaning": "horn", "stroke_count": 7, "reading": "つの" },
  { "id": 149, "character": "言", "meaning": "speech", "stroke_count": 7, "reading": "ことば" },
  { "id": 150, "character": "谷", "meaning": "valley", "stroke_count": 7, "reading": "たに" },
  { "id": 151, "character": "豆", "meaning": "bean", "stroke_count": 7, "reading": "まめ" },
  { "id": 152, "character": "豕", "meaning": "pig", "stroke_count": 7, "reading": "いのこ" },
  { "id": 153, "character": "豸", "meaning": "badger", "stroke_count": 7, "reading": "むじなへん" },
  { "id": 154, "character": "貝", "meaning": "shell", "stroke_count": 7, "reading": "かい" },
  { "id": 155, "character": "赤", "meaning": "red", "stroke_count": 7, "reading": "あか" },
  { "id": 156, "character": "走", "meaning": "run", "stroke_count": 7, "reading": "はしる" },
  { "id": 157, "character": "足", "meaning": "foot", "stroke_count": 7, "reading": "あし" },
  { "id": 158, "character": "身", "meaning": "body", "stroke_count": 7, "reading": "み" },
  { "id": 159, "character": "車", "meaning": "cart", "stroke_count": 7, "reading": "くるま" },
  { "id": 160, "character": "辛", "meaning": "bitter", "stroke_count": 7, "reading": "からい" },
  { "id": 161, "character": "辰", "meaning": "morning", "stroke_count": 7, "reading": "たつ" },
  { "id": 162, "character": "辵", "meaning": "walk", "stroke_count": 7, "reading": "しんにょう" },
  { "id": 163, "character": "邑", "meaning": "city", "stroke_count": 7, "reading": "おおざと" },
  { "id": 164, "character": "酉", "meaning": "wine", "stroke_count": 7, "reading": "とりへん" },
  { "id": 165, "character": "釆", "meaning": "distinguish", "stroke_count": 7, "reading": "のごめ" },
  { "id": 166, "character": "里", "meaning": "village", "stroke_count": 7, "reading": "さと" },
  { "id": 167, "character": "金", "meaning": "gold", "stroke_count": 8, "reading": "かね" },
  { "id": 168, "character": "長", "meaning": "long", "stroke_count": 8, "reading": "ながい" },
  { "id": 169, "character": "門", "meaning": "gate", "stroke_count": 8, "reading": "もん" },
  { "id": 170, "character": "阜", "meaning": "mound", "stroke_count": 8, "reading": "こざとへん" },
  { "id": 171, "character": "隶", "meaning": "slave", "stroke_count": 8, "reading": "れいづくり" },
  { "id": 172, "character": "隹", "meaning": "short-tailed bird", "stroke_count": 8, "reading": "ふるとり" },
  { "id": 173, "character": "雨", "meaning": "rain", "stroke_count": 8, "reading": "あめ" },
  { "id": 174, "character": "青", "meaning": "blue", "stroke_count": 8, "reading": "あお" },
  { "id": 175, "character": "非", "meaning": "wrong", "stroke_count": 8, "reading": "ひ" },
  { "id": 176, "character": "面", "meaning": "face", "stroke_count": 9, "reading": "めん" },
  { "id": 177, "character": "革", "meaning": "leather", "stroke_count": 9, "reading": "かわ" },
  { "id": 178, "character": "韋", "meaning": "tanned leather", "stroke_count": 9, "reading": "なめしがわ" },
  { "id": 179, "character": "韭", "meaning": "leek", "stroke_count": 9, "reading": "にら" },
  { "id": 180, "character": "音", "meaning": "sound", "stroke_count": 9, "reading": "おと" },
  { "id": 181, "character": "頁", "meaning": "leaf", "stroke_count": 9, "reading": "おおがい" },
  { "id": 182, "character": "風", "meaning": "wind", "stroke_count": 9, "reading": "かぜ" },
  { "id": 183, "character": "飛", "meaning": "fly", "stroke_count": 9, "reading": "とぶ" },
  { "id": 184, "character": "食", "meaning": "eat", "stroke_count": 9, "reading": "しょく" },
  { "id": 185, "character": "首", "meaning": "head", "stroke_count": 9, "reading": "くび" },
  { "id": 186, "character": "香", "meaning": "fragrant", "stroke_count": 9, "reading": "かおり" },
  { "id": 187, "character": "馬", "meaning": "horse", "stroke_count": 10, "reading": "うま" },
  { "id": 188, "character": "骨", "meaning": "bone", "stroke_count": 10, "reading": "ほね" },
  { "id": 189, "character": "高", "meaning": "tall", "stroke_count": 10, "reading": "たかい" },
  { "id": 190, "character": "髟", "meaning": "hair", "stroke_count": 10, "reading": "かみがしら" },
  { "id": 191, "character": "鬥", "meaning": "fight", "stroke_count": 10, "reading": "とうがまえ" },
  { "id": 192, "character": "鬯", "meaning": "sacrificial wine", "stroke_count": 10, "reading": "ちょう" },
  { "id": 193, "character": "鬲", "meaning": "cauldron", "stroke_count": 10, "reading": "かなえ" },
  { "id": 194, "character": "鬼", "meaning": "ghost", "stroke_count": 10, "reading": "おに" },
  { "id": 195, "character": "魚", "meaning": "fish", "stroke_count": 11, "reading": "うお" },
  { "id": 196, "character": "鳥", "meaning": "bird", "stroke_count": 11, "reading": "とり" },
  { "id": 197, "character": "鹵", "meaning": "salt", "stroke_count": 11, "reading": "ろ" },
  { "id": 198, "character": "鹿", "meaning": "deer", "stroke_count": 11, "reading": "しか" },
  { "id": 199, "character": "麦", "meaning": "wheat", "stroke_count": 11, "reading": "むぎ" },
  { "id": 200, "character": "麻", "meaning": "hemp", "stroke_count": 11, "reading": "あさ" },
  { "id": 201, "character": "黄", "meaning": "yellow", "stroke_count": 12, "reading": "き" },
  { "id": 202, "character": "黍", "meaning": "millet", "stroke_count": 12, "reading": "きび" },
  { "id": 203, "character": "黒", "meaning": "black", "stroke_count": 12, "reading": "くろ" },
  { "id": 204, "character": "黹", "meaning": "embroidery", "stroke_count": 12, "reading": "ぬいとり" },
  { "id": 205, "character": "黽", "meaning": "frog", "stroke_count": 13, "reading": "べんあし" },
  { "id": 206, "character": "鼎", "meaning": "tripod", "stroke_count": 13, "reading": "かなえ" },
  { "id": 207, "character": "鼓", "meaning": "drum", "stroke_count": 13, "reading": "つづみ" },
  { "id": 208, "character": "鼠", "meaning": "rat", "stroke_count": 13, "reading": "ねずみ" },
  { "id": 209, "character": "鼻", "meaning": "nose", "stroke_count": 14, "reading": "はな" },
  { "id": 210, "character": "齊", "meaning": "even", "stroke_count": 14, "reading": "せい" },
  { "id": 211, "character": "歯", "meaning": "tooth", "stroke_count": 15, "reading": "は" },
  { "id": 212, "character": "龍", "meaning": "dragon", "stroke_count": 16, "reading": "りゅう" },
  { "id": 213, "character": "龜", "meaning": "turtle", "stroke_count": 16, "reading": "かめ" },
  { "id": 214, "character": "龠", "meaning": "flute", "stroke_count": 17, "reading": "やく" }
]
